LICENSE
MANIFEST.in
README.md
setup.py
look_at/__init__.py
look_at/focus.py
look_at/wmctrl.py
look_at.egg-info/PKG-INFO
look_at.egg-info/SOURCES.txt
look_at.egg-info/dependency_links.txt
look_at.egg-info/entry_points.txt
look_at.egg-info/top_level.txt
look_at.egg-info/zip-safe
look_at/scripts/__init__.py
look_at/scripts/look_at.py