Metadata-Version: 1.1
Name: look-at
Version: 1.1
Summary: Command line window focus switcher
Home-page: UNKNOWN
Author: UNKNOWN
Author-email: UNKNOWN
License: BSD
Platform: All
Classifier: Development Status :: 4 - Beta
Classifier: License :: OSI Approved :: BSD License
Classifier: Operating System :: OS Independent
Classifier: Programming Language :: Python :: 2.5
Classifier: Programming Language :: Python :: 2.6
Classifier: Programming Language :: Python :: 2.7
Classifier: Programming Language :: Python :: 3.2
